{
    "backend": "api-server-nodejs",
    "db_name": "",
    "db_pass": "",
    "db_type": "sqlite",
    "db_user": "",
    "dbms": "1",
    "description": "generated product",
    "design": "datta-able",
    "docker": "1",
    "err_code": 0,
    "frontend": "react",
    "heroku": "0",
    "pattern": "fullstack",
    "pro": "0",
    "task_id": "450a409b-6608-4427-a41f-69eb4e5aab75",
    "task_info": "Upload Sources [0%] - 203 files",
    "task_output": "450a409b-6608-4427-a41f-69eb4e5aab75.zip",
    "task_result": "SUCCESS",
    "task_state": "RUNNING",
    "task_ts_end": "2022-11-23-10-57-07",
    "task_ts_start": "2022-11-23-10-57-04"
}